{
  "company_name": "GEOMANT UK LIMITED",
  "company_number": "05323859",
  "company_status": "active",
  "company_type": "ltd",
  "date_of_incorporation": "2005-01-05",
  "jurisdiction": "england-wales",
  "registered_address": "Turnpike Gate House, Alcester Heath, Alcester, Warwickshire, B49 5JG",
  "registered_address_structured": {
    "address_line_1": "Turnpike Gate House",
    "address_line_2": "Alcester Heath",
    "locality": "Alcester",
    "postal_code": "B49 5JG",
    "region": "Warwickshire"
  },
  "sic_codes": [
    "62090"
  ],
  "previous_company_names": [],
  "has_been_liquidated": false,
  "has_insolvency_history": false,
  "has_charges": false,
  "has_super_secure_pscs": false,
  "accounts": {
    "next_accounts_due_on": "2026-09-30",
    "next_accounts_period_end_on": "2025-12-31",
    "next_accounts_period_start_on": "2025-01-01",
    "next_accounts_overdue": false,
    "last_accounts_made_up_to": "2024-12-31",
    "last_accounts_type": "small",
    "accounting_reference_date_day": 31,
    "accounting_reference_date_month": 12
  },
  "confirmation_statement": {
    "next_due": "2027-01-19",
    "last_made_up_to": "2026-01-05",
    "next_made_up_to": "2027-01-05"
  },
  "officers": {
    "directors": [
      {
        "name": "ROSS, Kevin Frank",
        "officer_role": "director",
        "appointed_on": "2005-01-05",
        "date_of_birth_month": 7,
        "date_of_birth_year": 1963,
        "nationality": "British",
        "country_of_residence": "England",
        "address": {
          "address_line_1": "Alcester Heath",
          "locality": "Alcester",
          "postal_code": "B49 5JG",
          "premises": "Turnpike Gate House",
          "region": "Warwickshire"
        }
      },
      {
        "name": "VÉCSEI, Farkas Ákos",
        "officer_role": "director",
        "appointed_on": "2018-08-13",
        "date_of_birth_month": 6,
        "date_of_birth_year": 1971,
        "nationality": "Hungarian",
        "country_of_residence": "Hungary",
        "address": {
          "address_line_1": "Alcester Heath",
          "locality": "Alcester",
          "postal_code": "B49 5JG",
          "premises": "Turnpike Gate House",
          "region": "Warwickshire"
        }
      },
      {
        "name": "LAFONE-WARD, David",
        "officer_role": "director",
        "appointed_on": "2006-05-24",
        "resigned_on": "2018-08-13",
        "date_of_birth_month": 4,
        "date_of_birth_year": 1963,
        "nationality": "British",
        "country_of_residence": "Wales",
        "address": {
          "address_line_1": "Belfield House",
          "address_line_2": "Hilgay Road",
          "locality": "Brockweir",
          "postal_code": "NP16 7NU",
          "region": "Gloucestershire"
        }
      },
      {
        "name": "MARSH, Stuart",
        "officer_role": "director",
        "appointed_on": "2005-01-05",
        "resigned_on": "2019-09-19",
        "date_of_birth_month": 12,
        "date_of_birth_year": 1962,
        "nationality": "British",
        "country_of_residence": "Australia",
        "address": {
          "address_line_1": "8 Wilga Street",
          "country": "Australia",
          "locality": "Elenora Heights",
          "postal_code": "NSW 2101",
          "region": "Nsw 2101"
        }
      },
      {
        "name": "SIMON, Robert",
        "officer_role": "director",
        "appointed_on": "2005-05-01",
        "resigned_on": "2008-12-31",
        "date_of_birth_month": 7,
        "date_of_birth_year": 1973,
        "nationality": "Hungarian",
        "address": {
          "address_line_1": "Hungary 1201 Budapest",
          "address_line_2": "Berkenye St.1",
          "country": "Hungary",
          "locality": "Budapest",
          "region": "H-1201"
        }
      },
      {
        "name": "CODDAN MANAGERS SERVICE LIMITED",
        "officer_role": "corporate-director",
        "appointed_on": "2005-04-08",
        "resigned_on": "2006-05-24",
        "address": {
          "address_line_1": "Dept 706",
          "address_line_2": "78 Marylebone High Street",
          "locality": "London",
          "postal_code": "W1U 5AP"
        }
      },
      {
        "name": "HANOVER DIRECTORS LIMITED",
        "officer_role": "corporate-nominee-director",
        "appointed_on": "2005-01-05",
        "resigned_on": "2005-01-05",
        "address": {
          "address_line_1": "44 Upper Belgrave Road",
          "locality": "Bristol",
          "postal_code": "BS8 2XN"
        }
      }
    ],
    "secretaries": [
      {
        "name": "ROSS, Kevin Frank",
        "officer_role": "secretary",
        "appointed_on": "2005-01-05",
        "nationality": "British",
        "address": {
          "address_line_1": "Alcester Heath",
          "locality": "Alcester",
          "postal_code": "B49 5JG",
          "premises": "Turnpike Gate House",
          "region": "Warwickshire"
        }
      },
      {
        "name": "HCS SECRETARIAL LIMITED",
        "officer_role": "corporate-nominee-secretary",
        "appointed_on": "2005-01-05",
        "resigned_on": "2005-01-05",
        "address": {
          "address_line_1": "Upper Belgrave Road",
          "address_line_2": "Clifton",
          "country": "Uk",
          "locality": "Bristol",
          "postal_code": "BS8 2XN",
          "premises": "44"
        }
      }
    ]
  },
  "persons_with_significant_control": {
    "persons_with_significant_control": [
      {
        "name": "Geomant Global Ltd",
        "kind": "corporate-entity-person-with-significant-control",
        "natures_of_control": [
          "ownership-of-shares-75-to-100-percent",
          "voting-rights-75-to-100-percent"
        ],
        "notified_on": "2020-07-29",
        "address": {
          "address_line_1": "Heinzelova Ulica",
          "country": "Croatia",
          "locality": "Zagreb (City Of Zagreb)",
          "premises": "62/A"
        },
        "identification": {
          "legal_form": "Limited Liability Company",
          "legal_authority": "Companies Act",
          "country_registered": "Croatia",
          "place_registered": "Company Register",
          "registration_number": "081319383"
        }
      },
      {
        "name": "Concentric Technologies Limited",
        "kind": "corporate-entity-person-with-significant-control",
        "natures_of_control": [
          "ownership-of-shares-75-to-100-percent"
        ],
        "notified_on": "2016-04-06",
        "ceased_on": "2020-07-29",
        "address": {
          "address_line_1": "Alcester Heath",
          "country": "England",
          "locality": "Alcester",
          "postal_code": "B49 5JG",
          "premises": "Turnpike Gate House",
          "region": "Warwickshire"
        },
        "identification": {
          "legal_form": "Private Limited Company",
          "legal_authority": "The Companies Act 2006",
          "country_registered": "England",
          "place_registered": "Registrar Of Companies (England And Wales)",
          "registration_number": "09073600"
        }
      }
    ]
  },
  "charges": {
    "charges": [
      {
        "charge_code": "053238590001",
        "charge_number": 1,
        "classification": [
          {
            "type": "charge-description",
            "description": "A registered charge"
          }
        ],
        "created_on": "2021-01-12",
        "delivered_on": "2021-02-01",
        "particulars": {
          "contains_floating_charge": true,
          "floating_charge_covers_all": true
        },
        "persons_entitled": [
          {
            "name": "Geomant Global Limited"
          }
        ],
        "status": "outstanding"
      }
    ],
    "total_count": 1,
    "unsatisfied_count": 1,
    "satisfied_count": 0,
    "part_satisfied_count": 0
  },
  "filing_history": {
    "filing_history": [
      {
        "category": "confirmation-statement",
        "date": "2026-01-06",
        "description": "confirmation-statement-with-no-updates",
        "type": "CS01",
        "pages": 3,
        "barcode": "XET7QUCG",
        "transaction_id": "MzQ5NzgwNzg2N2FkaXF6a2N4"
      },
      {
        "category": "accounts",
        "date": "2025-04-09",
        "description": "accounts-with-accounts-type-small",
        "type": "AA",
        "pages": 7,
        "barcode": "ADZSYENC",
        "transaction_id": "MzQ2MTkzODY5MGFkaXF6a2N4"
      },
      {
        "category": "confirmation-statement",
        "date": "2025-01-09",
        "description": "confirmation-statement-with-no-updates",
        "type": "CS01",
        "pages": 3,
        "barcode": "XDTVRKGW",
        "transaction_id": "MzQ1MDQ3MjAzOWFkaXF6a2N4"
      },
      {
        "category": "accounts",
        "date": "2024-05-19",
        "description": "accounts-with-accounts-type-small",
        "type": "AA",
        "pages": 14,
        "barcode": "AD369CN6",
        "transaction_id": "MzQyMjEzNjk0MGFkaXF6a2N4"
      },
      {
        "category": "confirmation-statement",
        "date": "2024-01-09",
        "description": "confirmation-statement-with-no-updates",
        "type": "CS01",
        "pages": 3,
        "barcode": "XCUBTX34",
        "transaction_id": "MzQwNzAwMDc2NGFkaXF6a2N4"
      },
      {
        "category": "accounts",
        "date": "2023-05-04",
        "description": "accounts-with-accounts-type-small",
        "type": "AA",
        "pages": 8,
        "barcode": "XC2SJ3KG",
        "transaction_id": "MzM3ODUxNzk1NWFkaXF6a2N4"
      },
      {
        "category": "confirmation-statement",
        "date": "2023-01-12",
        "description": "confirmation-statement-with-no-updates",
        "type": "CS01",
        "pages": 3,
        "barcode": "XBV32ZX6",
        "transaction_id": "MzM2NTU2NTgwMGFkaXF6a2N4"
      },
      {
        "category": "accounts",
        "date": "2022-07-14",
        "description": "accounts-with-accounts-type-small",
        "type": "AA",
        "pages": 10,
        "barcode": "XB88628X",
        "transaction_id": "MzM0NTcxOTYyNWFkaXF6a2N4"
      },
      {
        "category": "confirmation-statement",
        "date": "2022-01-12",
        "description": "confirmation-statement-with-no-updates",
        "type": "CS01",
        "pages": 3,
        "barcode": "XAVJJKWG",
        "transaction_id": "MzMyNjQ3NTQzNWFkaXF6a2N4"
      },
      {
        "category": "accounts",
        "date": "2021-11-30",
        "description": "accounts-with-accounts-type-small",
        "type": "AA",
        "pages": 9,
        "barcode": "XAICZPXV",
        "transaction_id": "MzMyMTg0NzU0NGFkaXF6a2N4"
      },
      {
        "category": "confirmation-statement",
        "date": "2021-02-01",
        "description": "confirmation-statement-with-updates",
        "type": "CS01",
        "pages": 5,
        "barcode": "X9XEYYEB",
        "transaction_id": "MzI5MDE5NDA2NWFkaXF6a2N4"
      },
      {
        "category": "mortgage",
        "date": "2021-02-01",
        "description": "mortgage-create-with-deed-with-charge-number-charge-creation-date",
        "type": "MR01",
        "pages": 8,
        "barcode": "X9XEYOO8",
        "transaction_id": "MzI5MDE5MTgyOWFkaXF6a2N4"
      },
      {
        "category": "persons-with-significant-control",
        "date": "2020-08-20",
        "description": "cessation-of-a-person-with-significant-control",
        "type": "PSC07",
        "pages": 1,
        "barcode": "X9BTN480",
        "transaction_id": "MzI3NTc2OTMwMmFkaXF6a2N4"
      },
      {
        "category": "persons-with-significant-control",
        "date": "2020-08-20",
        "description": "notification-of-a-person-with-significant-control",
        "type": "PSC02",
        "pages": 2,
        "barcode": "X9BTN3OP",
        "transaction_id": "MzI3NTc2OTI1M2FkaXF6a2N4"
      },
      {
        "category": "accounts",
        "date": "2020-07-28",
        "description": "accounts-with-accounts-type-total-exemption-full",
        "type": "AA",
        "pages": 9,
        "barcode": "X9A7NLT7",
        "transaction_id": "MzI3NDAzOTM3M2FkaXF6a2N4"
      },
      {
        "category": "confirmation-statement",
        "date": "2020-01-16",
        "description": "confirmation-statement-with-no-updates",
        "type": "CS01",
        "pages": 3,
        "barcode": "X8WSYRI4",
        "transaction_id": "MzI1NDcyNTUxNmFkaXF6a2N4"
      },
      {
        "category": "officers",
        "date": "2020-01-16",
        "description": "change-person-director-company-with-change-date",
        "type": "CH01",
        "pages": 2,
        "barcode": "X8WSYQE9",
        "transaction_id": "MzI1NDcyNTI1MmFkaXF6a2N4"
      },
      {
        "category": "officers",
        "date": "2020-01-16",
        "description": "change-person-secretary-company-with-change-date",
        "type": "CH03",
        "pages": 1,
        "barcode": "X8WSYQ4R",
        "transaction_id": "MzI1NDcyNTE1MWFkaXF6a2N4"
      },
      {
        "category": "accounts",
        "date": "2019-09-27",
        "description": "accounts-with-accounts-type-total-exemption-full",
        "type": "AA",
        "pages": 9,
        "barcode": "X8EV68XE",
        "transaction_id": "MzI0NTM2OTQ3MWFkaXF6a2N4"
      },
      {
        "category": "officers",
        "date": "2019-09-20",
        "description": "termination-director-company-with-name-termination-date",
        "type": "TM01",
        "pages": 1,
        "barcode": "X8EF1XZN",
        "transaction_id": "MzI0NDcyMTg3NmFkaXF6a2N4"
      },
      {
        "category": "confirmation-statement",
        "date": "2019-01-18",
        "description": "confirmation-statement-with-no-updates",
        "type": "CS01",
        "pages": 3,
        "barcode": "X7XFJHDF",
        "transaction_id": "MzIyNDgyMTA1OGFkaXF6a2N4"
      },
      {
        "category": "accounts",
        "date": "2018-09-25",
        "description": "accounts-with-accounts-type-total-exemption-full",
        "type": "AA",
        "pages": 9,
        "barcode": "X7F8HN3D",
        "transaction_id": "MzIxNTMzNTc5NWFkaXF6a2N4"
      },
      {
        "category": "officers",
        "date": "2018-08-21",
        "description": "termination-director-company-with-name-termination-date",
        "type": "TM01",
        "pages": 1,
        "barcode": "X7CTEN22",
        "transaction_id": "MzIxMjU1OTk4MmFkaXF6a2N4"
      },
      {
        "category": "officers",
        "date": "2018-08-21",
        "description": "appoint-person-director-company-with-name-date",
        "type": "AP01",
        "pages": 2,
        "barcode": "X7CTEMT4",
        "transaction_id": "MzIxMjU1OTk2MmFkaXF6a2N4"
      },
      {
        "category": "confirmation-statement",
        "date": "2018-01-19",
        "description": "confirmation-statement-with-no-updates",
        "type": "CS01",
        "pages": 3,
        "barcode": "X6XY0RVD",
        "transaction_id": "MzE5NTY4NDczMGFkaXF6a2N4"
      }
    ],
    "total_count": 73,
    "recent_filings_count": 2
  },
  "financials": {
    "employees": 10
  },
  "enrichment": {
    "website": "https://Geomant.com",
    "headcount": 10,
    "tech_stack": [
      "Microsoft Teams",
      "Skype for Business"
    ],
    "business_keywords": [
      "unified engagement solutions",
      "contact center",
      "customer interactions",
      "omnichannel service",
      "real-time dashboards",
      "historical dashboards",
      "digital journey offerings",
      "compliance recording",
      "CRM solutions",
      "multi-channel software",
      "IVR",
      "auto attendant",
      "automated distribution",
      "customer experience",
      "technology integration"
    ],
    "services": [
      "Real-time and historical dashboards for management, agent desktops, and in-center wallboards (Geomant Wallboard)",
      "Next-generation digital journey offerings for personal customer service (Geomant Digital)",
      "Compliance recording, monitoring, and retrieval of communications across Microsoft Teams",
      "Unifying contact center and CRM solutions to provide a single agent interface (Desktop Connect)",
      "Multi-channel software for Skype for Business including IVR, auto attendant, and automated distribution (Contact Expert)",
      "Consultation and expert engagement to understand business requirements and challenges",
      "Infrastructure survey and improvement identification",
      "Strategy and implementation planning for proposed solutions",
      "Seamless deployment, rigorous testing, and staff training"
    ],
    "customer_segments": [
      "contact centers",
      "businesses seeking customer interaction solutions",
      "organizations using Microsoft Teams for communications",
      "enterprises requiring CRM integration",
      "companies needing compliance recording",
      "retail sector (implied by 'Retail Rush' reference)"
    ],
    "business_description": "Geomant, now part of Graia, provides unified engagement solutions focused on revolutionizing customer interactions through faster resolutions and seamless omnichannel service. The company offers specialized products and services for contact centers, including real-time dashboards, compliance recording, digital journey offerings, and CRM integration, alongside tailored implementation and support.",
    "enrichment_status": "completed",
    "msp_likelihood_score": 20,
    "msp_likelihood_confidence": "medium",
    "msp_likelihood_computed_at": "2026-01-10T02:37:19.345Z"
  },
  "scraped_at": "2026-01-10T02:37:10.705Z",
  "updated_at": "2026-01-10T02:37:19.345Z",
  "version": 1
}
