{
  "company_name": "WHITE ROOM CONSORTIUM LIMITED",
  "company_number": "07768048",
  "company_status": "active",
  "company_type": "ltd",
  "date_of_incorporation": "2011-09-09",
  "jurisdiction": "england-wales",
  "registered_address": "The Deep Business Centre, Tower Street, Hull, HU1 4BG",
  "registered_address_structured": {
    "address_line_1": "The Deep Business Centre",
    "address_line_2": "Tower Street",
    "locality": "Hull",
    "postal_code": "HU1 4BG"
  },
  "sic_codes": [
    "62090"
  ],
  "previous_company_names": [],
  "has_been_liquidated": false,
  "has_insolvency_history": false,
  "has_charges": false,
  "has_super_secure_pscs": false,
  "accounts": {
    "next_accounts_due_on": "2026-06-30",
    "next_accounts_period_end_on": "2025-09-30",
    "next_accounts_period_start_on": "2024-10-01",
    "next_accounts_overdue": false,
    "last_accounts_made_up_to": "2024-09-30",
    "last_accounts_type": "unaudited-abridged",
    "accounting_reference_date_day": 30,
    "accounting_reference_date_month": 9
  },
  "confirmation_statement": {
    "next_due": "2026-09-23",
    "last_made_up_to": "2025-09-09",
    "next_made_up_to": "2026-09-09"
  },
  "officers": {
    "directors": [
      {
        "name": "DUNNE, Eamonn Joseph",
        "officer_role": "director",
        "appointed_on": "2011-09-09",
        "date_of_birth_month": 3,
        "date_of_birth_year": 1969,
        "nationality": "British",
        "country_of_residence": "United Kingdom",
        "address": {
          "address_line_1": "Tower Street",
          "country": "England",
          "locality": "Hull",
          "postal_code": "HU1 4BG",
          "premises": "The Deep Business Centre"
        }
      },
      {
        "name": "MCKIE, Christopher Andrew",
        "officer_role": "director",
        "appointed_on": "2011-09-09",
        "date_of_birth_month": 10,
        "date_of_birth_year": 1969,
        "nationality": "British",
        "country_of_residence": "England",
        "address": {
          "address_line_1": "Tower Street",
          "country": "England",
          "locality": "Hull",
          "postal_code": "HU1 4BG",
          "premises": "The Deep Business Centre"
        }
      }
    ],
    "secretaries": [
      {
        "name": "DUNNE, Eamonn",
        "officer_role": "secretary",
        "appointed_on": "2011-09-09",
        "address": {
          "address_line_1": "Tower Street",
          "country": "England",
          "locality": "Hull",
          "postal_code": "HU1 4BG",
          "premises": "The Deep Business Centre"
        }
      }
    ]
  },
  "persons_with_significant_control": {
    "persons_with_significant_control": [
      {
        "name": "Mr Chris Mckie",
        "kind": "individual-person-with-significant-control",
        "natures_of_control": [
          "ownership-of-shares-25-to-50-percent"
        ],
        "notified_on": "2016-09-09",
        "date_of_birth_month": 10,
        "date_of_birth_year": 1969,
        "nationality": "British",
        "country_of_residence": "England",
        "address": {
          "address_line_1": "Tower Street",
          "locality": "Hull",
          "postal_code": "HU1 4BG",
          "premises": "The Deep Business Centre"
        }
      },
      {
        "name": "Mr Eamonn Joseph Dunne",
        "kind": "individual-person-with-significant-control",
        "natures_of_control": [
          "ownership-of-shares-25-to-50-percent"
        ],
        "notified_on": "2016-09-09",
        "date_of_birth_month": 3,
        "date_of_birth_year": 1969,
        "nationality": "Irish",
        "country_of_residence": "England",
        "address": {
          "address_line_1": "Tower Street",
          "locality": "Hull",
          "postal_code": "HU1 4BG",
          "premises": "The Deep Business Centre"
        }
      }
    ]
  },
  "charges": {
    "charges": [],
    "total_count": 0,
    "unsatisfied_count": 0,
    "satisfied_count": 0,
    "part_satisfied_count": 0
  },
  "filing_history": {
    "filing_history": [
      {
        "category": "confirmation-statement",
        "date": "2025-09-11",
        "description": "confirmation-statement-with-no-updates",
        "type": "CS01",
        "pages": 3,
        "barcode": "XEAW2BMW",
        "transaction_id": "MzQ4MDcxOTg2M2FkaXF6a2N4"
      },
      {
        "category": "accounts",
        "date": "2025-05-27",
        "description": "accounts-with-accounts-type-unaudited-abridged",
        "type": "AA",
        "pages": 8,
        "barcode": "XE3FZ0A0",
        "transaction_id": "MzQ2Nzg5NzM5MmFkaXF6a2N4"
      },
      {
        "category": "confirmation-statement",
        "date": "2024-09-19",
        "description": "confirmation-statement-with-no-updates",
        "type": "CS01",
        "pages": 3,
        "barcode": "XDC078Q0",
        "transaction_id": "MzQzNjUxMTE1MGFkaXF6a2N4"
      },
      {
        "category": "accounts",
        "date": "2024-06-28",
        "description": "accounts-with-accounts-type-unaudited-abridged",
        "type": "AA",
        "pages": 8,
        "barcode": "XD692FOZ",
        "transaction_id": "MzQyNzAwOTY4OWFkaXF6a2N4"
      },
      {
        "category": "confirmation-statement",
        "date": "2023-09-14",
        "description": "confirmation-statement-with-no-updates",
        "type": "CS01",
        "pages": 3,
        "barcode": "XCC18DG1",
        "transaction_id": "MzM5MzEzMjE0OWFkaXF6a2N4"
      },
      {
        "category": "accounts",
        "date": "2023-06-07",
        "description": "accounts-with-accounts-type-unaudited-abridged",
        "type": "AA",
        "pages": 8,
        "barcode": "XC56CUP5",
        "transaction_id": "MzM4MjIxMTI3NWFkaXF6a2N4"
      },
      {
        "category": "confirmation-statement",
        "date": "2022-09-12",
        "description": "confirmation-statement-with-no-updates",
        "type": "CS01",
        "pages": 3,
        "barcode": "XBCDNNNL",
        "transaction_id": "MzM1MTYzMDQ3N2FkaXF6a2N4"
      },
      {
        "category": "accounts",
        "date": "2022-04-14",
        "description": "accounts-with-accounts-type-unaudited-abridged",
        "type": "AA",
        "pages": 8,
        "barcode": "XB1WB1SI",
        "transaction_id": "MzMzNjMwOTk3MGFkaXF6a2N4"
      },
      {
        "category": "confirmation-statement",
        "date": "2021-09-13",
        "description": "confirmation-statement-with-no-updates",
        "type": "CS01",
        "pages": 3,
        "barcode": "XACXBJM0",
        "transaction_id": "MzMxMzY5MTE1M2FkaXF6a2N4"
      },
      {
        "category": "accounts",
        "date": "2021-06-03",
        "description": "accounts-with-accounts-type-unaudited-abridged",
        "type": "AA",
        "pages": 8,
        "barcode": "XA5VEE22",
        "transaction_id": "MzMwMzI1OTAyNmFkaXF6a2N4"
      },
      {
        "category": "confirmation-statement",
        "date": "2020-09-15",
        "description": "confirmation-statement-with-no-updates",
        "type": "CS01",
        "pages": 3,
        "barcode": "X9DNO0CI",
        "transaction_id": "MzI3NzcxMzEwOGFkaXF6a2N4"
      },
      {
        "category": "accounts",
        "date": "2020-04-07",
        "description": "accounts-with-accounts-type-unaudited-abridged",
        "type": "AA",
        "pages": 8,
        "barcode": "X92HCDNC",
        "transaction_id": "MzI2MTkxMzgxN2FkaXF6a2N4"
      },
      {
        "category": "confirmation-statement",
        "date": "2019-09-16",
        "description": "confirmation-statement-with-no-updates",
        "type": "CS01",
        "pages": 3,
        "barcode": "X8E4HMLC",
        "transaction_id": "MzI0NDM1MTQxNGFkaXF6a2N4"
      },
      {
        "category": "accounts",
        "date": "2019-04-10",
        "description": "accounts-with-accounts-type-unaudited-abridged",
        "type": "AA",
        "pages": 8,
        "barcode": "X8341EEP",
        "transaction_id": "MzIzMTczNzc4OGFkaXF6a2N4"
      },
      {
        "category": "confirmation-statement",
        "date": "2018-10-03",
        "description": "confirmation-statement-with-no-updates",
        "type": "CS01",
        "pages": 3,
        "barcode": "X7FRCDGP",
        "transaction_id": "MzIxNjE0MzI0MmFkaXF6a2N4"
      },
      {
        "category": "accounts",
        "date": "2018-06-25",
        "description": "accounts-with-accounts-type-unaudited-abridged",
        "type": "AA",
        "pages": 8,
        "barcode": "X78TSDMH",
        "transaction_id": "MzIwODE3NzMxNGFkaXF6a2N4"
      },
      {
        "category": "confirmation-statement",
        "date": "2017-09-22",
        "description": "confirmation-statement-with-no-updates",
        "type": "CS01",
        "pages": 3,
        "barcode": "X6FHYYWP",
        "transaction_id": "MzE4NTk3OTUxNGFkaXF6a2N4"
      },
      {
        "category": "accounts",
        "date": "2017-02-20",
        "description": "accounts-with-accounts-type-total-exemption-small",
        "type": "AA",
        "pages": 6,
        "barcode": "X60N69V5",
        "transaction_id": "MzE2OTMwNDA4NWFkaXF6a2N4"
      },
      {
        "category": "confirmation-statement",
        "date": "2016-09-15",
        "description": "confirmation-statement-with-updates",
        "type": "CS01",
        "pages": 7,
        "barcode": "X5FL0796",
        "transaction_id": "MzE1NzQ2NjU4OWFkaXF6a2N4"
      },
      {
        "category": "accounts",
        "date": "2016-01-29",
        "description": "accounts-with-accounts-type-total-exemption-small",
        "type": "AA",
        "pages": 6,
        "barcode": "X4ZNLPVT",
        "transaction_id": "MzE0MDgyMTc0OWFkaXF6a2N4"
      },
      {
        "category": "capital",
        "date": "2015-09-29",
        "description": "capital-allotment-shares",
        "type": "SH01",
        "pages": 3,
        "barcode": "X4GYFMBV",
        "transaction_id": "MzEzMTk4MTkxOWFkaXF6a2N4"
      },
      {
        "category": "annual-return",
        "date": "2015-09-25",
        "description": "annual-return-company-with-made-up-date-full-list-shareholders",
        "type": "AR01",
        "pages": 5,
        "barcode": "X4GO3WSH",
        "transaction_id": "MzEzMTc3NjU3NmFkaXF6a2N4"
      },
      {
        "category": "accounts",
        "date": "2014-12-04",
        "description": "accounts-with-accounts-type-total-exemption-small",
        "type": "AA",
        "pages": 6,
        "barcode": "X3LZZK8R",
        "transaction_id": "MzExMjgwMTE0MGFkaXF6a2N4"
      },
      {
        "category": "annual-return",
        "date": "2014-10-20",
        "description": "annual-return-company-with-made-up-date-full-list-shareholders",
        "type": "AR01",
        "pages": 5,
        "barcode": "X3IVYJM1",
        "transaction_id": "MzEwOTczNTE1NmFkaXF6a2N4"
      },
      {
        "category": "accounts",
        "date": "2014-01-27",
        "description": "accounts-with-accounts-type-total-exemption-small",
        "type": "AA",
        "pages": 6,
        "barcode": "X30HIUSO",
        "transaction_id": "MzA5MzM1MzcyN2FkaXF6a2N4"
      }
    ],
    "total_count": 30,
    "recent_filings_count": 2
  },
  "financials": {
    "employees": 8
  },
  "enrichment": {
    "website": "https://Miford.co.uk",
    "headcount": 8,
    "enrichment_status": "pending"
  },
  "version": 1,
  "updated_at": "2026-01-10T09:51:39.003Z",
  "scraped_at": "2026-01-10T09:51:39.003Z"
}
