{
  "company_name": "TRUSTBRIDGE (UK) LIMITED",
  "company_number": "08026086",
  "company_status": "active",
  "company_type": "ltd",
  "date_of_incorporation": "2012-04-11",
  "jurisdiction": "england-wales",
  "registered_address": "111a Station Road, West Wickham, Kent, BR4 0PX",
  "registered_address_structured": {
    "address_line_1": "111a Station Road",
    "locality": "West Wickham",
    "postal_code": "BR4 0PX",
    "region": "Kent"
  },
  "sic_codes": [
    "62020"
  ],
  "previous_company_names": [],
  "has_been_liquidated": false,
  "has_insolvency_history": false,
  "has_charges": false,
  "has_super_secure_pscs": false,
  "accounts": {
    "next_accounts_due_on": "2026-01-31",
    "next_accounts_period_end_on": "2025-04-30",
    "next_accounts_period_start_on": "2024-05-01",
    "next_accounts_overdue": false,
    "last_accounts_made_up_to": "2024-04-30",
    "last_accounts_type": "total-exemption-full",
    "accounting_reference_date_day": 30,
    "accounting_reference_date_month": 4
  },
  "confirmation_statement": {
    "next_due": "2026-08-29",
    "last_made_up_to": "2025-08-15",
    "next_made_up_to": "2026-08-15"
  },
  "officers": {
    "directors": [
      {
        "name": "DIXON, David Robert",
        "officer_role": "director",
        "appointed_on": "2012-04-11",
        "date_of_birth_month": 8,
        "date_of_birth_year": 1977,
        "nationality": "English",
        "country_of_residence": "United Kingdom",
        "address": {
          "address_line_1": "Station Road",
          "country": "United Kingdom",
          "locality": "West Wickham",
          "postal_code": "BR4 0PX",
          "premises": "111a",
          "region": "Kent"
        }
      },
      {
        "name": "LESTER-BUSH, David Philip",
        "officer_role": "director",
        "appointed_on": "2013-04-08",
        "resigned_on": "2022-11-01",
        "date_of_birth_month": 5,
        "date_of_birth_year": 1980,
        "nationality": "British",
        "country_of_residence": "United Kingdom",
        "address": {
          "address_line_1": "Station Road",
          "country": "United Kingdom",
          "locality": "West Wickham",
          "postal_code": "BR4 0PX",
          "premises": "111a",
          "region": "Kent"
        }
      }
    ],
    "secretaries": []
  },
  "persons_with_significant_control": {
    "persons_with_significant_control": [
      {
        "name": "Mr David Philip Lester-Bush",
        "kind": "individual-person-with-significant-control",
        "natures_of_control": [
          "ownership-of-shares-25-to-50-percent"
        ],
        "notified_on": "2017-04-08",
        "ceased_on": "2022-11-01",
        "date_of_birth_month": 5,
        "date_of_birth_year": 1980,
        "nationality": "British",
        "country_of_residence": "United Kingdom",
        "address": {
          "address_line_1": "Station Road",
          "locality": "West Wickham",
          "postal_code": "BR4 0PX",
          "premises": "111a",
          "region": "Kent"
        }
      },
      {
        "name": "Mr David Robert Dixon",
        "kind": "individual-person-with-significant-control",
        "natures_of_control": [
          "ownership-of-shares-75-to-100-percent"
        ],
        "notified_on": "2017-04-08",
        "date_of_birth_month": 8,
        "date_of_birth_year": 1977,
        "nationality": "English",
        "country_of_residence": "United Kingdom",
        "address": {
          "address_line_1": "Station Road",
          "locality": "West Wickham",
          "postal_code": "BR4 0PX",
          "premises": "111a",
          "region": "Kent"
        }
      }
    ]
  },
  "charges": {
    "charges": [],
    "total_count": 0,
    "unsatisfied_count": 0,
    "satisfied_count": 0,
    "part_satisfied_count": 0
  },
  "filing_history": {
    "filing_history": [
      {
        "category": "confirmation-statement",
        "date": "2025-10-17",
        "description": "confirmation-statement-with-no-updates",
        "type": "CS01",
        "pages": 3,
        "barcode": "XEDDZ4R7",
        "transaction_id": "MzQ4NTM0NTgxMmFkaXF6a2N4"
      },
      {
        "category": "accounts",
        "date": "2025-01-31",
        "description": "accounts-with-accounts-type-total-exemption-full",
        "type": "AA",
        "pages": 7,
        "barcode": "XDVDVZEZ",
        "transaction_id": "MzQ1MzI3Nzc4MWFkaXF6a2N4"
      },
      {
        "category": "gazette",
        "date": "2024-11-06",
        "description": "gazette-filings-brought-up-to-date",
        "type": "DISS40",
        "pages": 1,
        "transaction_id": "MzQ0MTc0OTY3NWFkaXF6a2N4"
      },
      {
        "category": "gazette",
        "date": "2024-11-05",
        "description": "gazette-notice-compulsory",
        "type": "GAZ1",
        "pages": 1,
        "transaction_id": "MzQ0MDkwODg1OGFkaXF6a2N4"
      },
      {
        "category": "confirmation-statement",
        "date": "2024-11-01",
        "description": "confirmation-statement-with-no-updates",
        "type": "CS01",
        "pages": 3,
        "barcode": "XDEYCEHK",
        "transaction_id": "MzQ0MTc0OTU5NmFkaXF6a2N4"
      },
      {
        "category": "accounts",
        "date": "2024-01-30",
        "description": "accounts-with-accounts-type-total-exemption-full",
        "type": "AA",
        "pages": 7,
        "barcode": "XCVTD3FT",
        "transaction_id": "MzQwOTI4Nzk5MWFkaXF6a2N4"
      },
      {
        "category": "confirmation-statement",
        "date": "2023-08-15",
        "description": "confirmation-statement-with-updates",
        "type": "CS01",
        "pages": 4,
        "barcode": "XC9Y7V1D",
        "transaction_id": "MzM4OTU5ODg2NWFkaXF6a2N4"
      },
      {
        "category": "confirmation-statement",
        "date": "2023-02-20",
        "description": "confirmation-statement-with-updates",
        "type": "CS01",
        "pages": 4,
        "barcode": "XBXRJT61",
        "transaction_id": "MzM2OTg4Nzc1MGFkaXF6a2N4"
      },
      {
        "category": "accounts",
        "date": "2023-01-31",
        "description": "accounts-with-accounts-type-total-exemption-full",
        "type": "AA",
        "pages": 8,
        "barcode": "XBWCNTHU",
        "transaction_id": "MzM2NzcxMjg4NGFkaXF6a2N4"
      },
      {
        "category": "capital",
        "date": "2023-01-12",
        "description": "capital-cancellation-shares",
        "type": "SH06",
        "pages": 6,
        "barcode": "ABUOSISH",
        "transaction_id": "MzM2NTUyOTc1OGFkaXF6a2N4"
      },
      {
        "category": "capital",
        "date": "2023-01-12",
        "description": "capital-return-purchase-own-shares",
        "type": "SH03",
        "pages": 4,
        "barcode": "ABUOSIS9",
        "transaction_id": "MzM2NTUyOTc1N2FkaXF6a2N4"
      },
      {
        "category": "persons-with-significant-control",
        "date": "2022-11-02",
        "description": "change-to-a-person-with-significant-control",
        "type": "PSC04",
        "pages": 2,
        "barcode": "XBFYMU6P",
        "transaction_id": "MzM1NzMwMzQ4OWFkaXF6a2N4"
      },
      {
        "category": "persons-with-significant-control",
        "date": "2022-11-02",
        "description": "cessation-of-a-person-with-significant-control",
        "type": "PSC07",
        "pages": 1,
        "barcode": "XBFYMRC0",
        "transaction_id": "MzM1NzMwMjgwMmFkaXF6a2N4"
      },
      {
        "category": "officers",
        "date": "2022-11-02",
        "description": "termination-director-company-with-name-termination-date",
        "type": "TM01",
        "pages": 1,
        "barcode": "XBFYMQGO",
        "transaction_id": "MzM1NzMwMjUzOGFkaXF6a2N4"
      },
      {
        "category": "confirmation-statement",
        "date": "2022-06-14",
        "description": "confirmation-statement-with-no-updates",
        "type": "CS01",
        "pages": 3,
        "barcode": "XB64UE7E",
        "transaction_id": "MzM0MjQ3ODg5NGFkaXF6a2N4"
      },
      {
        "category": "accounts",
        "date": "2022-01-31",
        "description": "accounts-with-accounts-type-total-exemption-full",
        "type": "AA",
        "pages": 7,
        "barcode": "XAWVK93S",
        "transaction_id": "MzMyODMzMTk1OGFkaXF6a2N4"
      },
      {
        "category": "confirmation-statement",
        "date": "2021-06-04",
        "description": "confirmation-statement-with-no-updates",
        "type": "CS01",
        "pages": 3,
        "barcode": "XA5Y4D5S",
        "transaction_id": "MzMwMzQzNDc5M2FkaXF6a2N4"
      },
      {
        "category": "accounts",
        "date": "2021-04-07",
        "description": "accounts-with-accounts-type-total-exemption-full",
        "type": "AA",
        "pages": 7,
        "barcode": "XA1WDAWR",
        "transaction_id": "MzI5NzAyNjYwMWFkaXF6a2N4"
      },
      {
        "category": "confirmation-statement",
        "date": "2020-05-14",
        "description": "confirmation-statement-with-no-updates",
        "type": "CS01",
        "pages": 3,
        "barcode": "X951MN3S",
        "transaction_id": "MzI2NDc2OTg2NWFkaXF6a2N4"
      },
      {
        "category": "accounts",
        "date": "2020-01-27",
        "description": "accounts-with-accounts-type-total-exemption-full",
        "type": "AA",
        "pages": 8,
        "barcode": "X8XJJ5X5",
        "transaction_id": "MzI1NTY1NjQyMGFkaXF6a2N4"
      },
      {
        "category": "confirmation-statement",
        "date": "2019-05-03",
        "description": "confirmation-statement-with-no-updates",
        "type": "CS01",
        "pages": 3,
        "barcode": "X84NSQ3K",
        "transaction_id": "MzIzMzYyNzI1NmFkaXF6a2N4"
      },
      {
        "category": "accounts",
        "date": "2019-01-15",
        "description": "accounts-with-accounts-type-total-exemption-full",
        "type": "AA",
        "pages": 7,
        "barcode": "X7X7IXOF",
        "transaction_id": "MzIyNDUwNTMwMGFkaXF6a2N4"
      },
      {
        "category": "confirmation-statement",
        "date": "2018-05-25",
        "description": "confirmation-statement-with-no-updates",
        "type": "CS01",
        "pages": 3,
        "barcode": "X76OW9RT",
        "transaction_id": "MzIwNTg5MDI4OGFkaXF6a2N4"
      },
      {
        "category": "accounts",
        "date": "2018-01-29",
        "description": "accounts-with-accounts-type-total-exemption-full",
        "type": "AA",
        "pages": 7,
        "barcode": "X6YOLSKP",
        "transaction_id": "MzE5NjM5NTMwNmFkaXF6a2N4"
      },
      {
        "category": "confirmation-statement",
        "date": "2017-05-22",
        "description": "confirmation-statement-with-updates",
        "type": "CS01",
        "pages": 6,
        "barcode": "X66ZDPOQ",
        "transaction_id": "MzE3NjI3OTU2NmFkaXF6a2N4"
      }
    ],
    "total_count": 36,
    "recent_filings_count": 2
  },
  "financials": {
    "employees": 11
  },
  "enrichment": {
    "headcount": 11,
    "enrichment_status": "pending"
  },
  "version": 1,
  "updated_at": "2026-01-10T10:38:49.436Z",
  "scraped_at": "2026-01-10T10:38:49.436Z"
}
